ESTRUCTURAL/inversor.v
module inversor (
    input wire entrada,
    output wire salida
);
    assign salida = ~entrada;
endmodule

ESTRUCTURAL/celda_final_e.v
// Implementacion estructural de la celda final  de derecha a izquierda
// Entrada W que es la entrada de la celda tipica y con una salida de Z
module celda_final_e (
    input wire W,
    input wire A,
    input wire B,
    output wire Z
);

// Cable para conectar a la compuerta 
wire W_neg;

// INVERSOR PARA GENERAR !W que al final se obitne Z=!W
inversor inversorW_cf (
    .entrada(W),
    .salida(Z)
 );
endmodule

ESTRUCTURAL/Comp_OR.v
module Comp_OR (
    input wire A_or,
    input wire B_or,
    output wire OR
);
    assign OR = A_or | B_or;
endmodule

ESTRUCTURAL/Comp_AND.v
module Comp_AND (
    input wire  A_and,
    input wire  B_and,
    output wire AND
);
    assign AND = A_and & B_and;
endmodule

ESTRUCTURAL/celda_tipica_e.v
// Implementacion estructural de la celda tipica  de derecha a izquierda
// Entradas A, B y w con una salida W
module celda_tipica_e (
    input wire A, B, w,
    output wire W
);

// Cables para conectar a las compuertas
wire B_neg;
wire wB_neg_OR;
wire wA_OR;
wire AB_neg_OR;
wire OR1;

// INVERSOR PARA GENERAR !B
inversor inversorB (
    .entrada(B),
    .salida(B_neg)
);

// COMPUERTAS AND 
//Con entrada w y !B y una salida w!B que va hacia la compuerta OR 1
Comp_AND comp_AND_ct1 (
    .A_and(w),
    .B_and(B_neg),
    .AND(wB_neg_OR)
);
//Con entrada w y A y una salida wA que va hacia la compuerta OR 1
Comp_AND comp_AND_ct2 (
    .A_and(w),
    .B_and(A),
    .AND(wA_OR)
);
//Con entrada A y !B y una salida A!B que va hacia la compuerta OR 2
Comp_AND comp_AND_ct3 (
    .A_and(A),
    .B_and(B_neg),
    .AND(AB_neg_OR)
);
 // COMPUERTAS OR
 //Con entrada w!B y wA y una salida OR1 que va hacia la compuerta OR 2
 Comp_OR comp_OR_ct1 (
   .A_or (wB_neg_OR),
   .B_or (wA_OR),
   .OR (OR1)
 );
 //Con entrada OR1 y A!B y una salida W
 Comp_OR comp_OR_ct2 (
   .A_or (OR1),
   .B_or (AB_neg_OR),
   .OR (W)
 );
endmodule

ESTRUCTURAL/celda_inicial_e.v
// Implementacion estructural de la celda inicial  de derecha a izquierda
// Entradas A y B con una salida W
module celda_inicial_e (
    input wire A,
    input wire B,
    output wire W
);

// Cables para conectar a las compuertas
wire B_neg;

// INVERSOR PARA GENERAR !B
inversor inversorB (
    .entrada(B),
    .salida(B_neg)
);

// COMPUERTA AND con entrada A y !B y una salida W
Comp_AND comp_AND_ci (
    .A_and(A),
    .B_and(B_neg),
    .AND(W)
);
endmodule

ESTRUCTURAL/Comparador .v
//Proyecto Final de Digitales,C01263,B82600,B86941.Implementacion Estructural, caso DERECHA a IZQUIERDA.
`include "celda_inicial_e.v"
`include "celda_tipica_e.v"
`include "celda_final_e.v"
`include "Comp_AND.v"
`include "Comp_OR.v"
`include "inversor.v"
//Como es implementacion estructural, se llaman los archivos de las compuertas logicas, junto las celdas tipicas.
module Comparador #(parameter N = 1)(
    input wire [N-1:0] A, //definiendo los tamanos de A, B y W
    input wire [N-1:0] B,
    output wire  W_out);
    wire [N:0] W_temp;

    celda_inicial_e uut_inicial(
        .A(A[0]),               //Conectamos todos los puertos a los bits iniciales
        .B(B[0]),
        .W(W_temp[0])
    );
    genvar i;
    generate
        for (i = 0; i < N; i=i +1 ) begin: gen_celdas //Bucle For para generar las celdas tipicas en base al parametro N.
                                                        //i=0 inicia el bucle en 0, i<N es la condicion que debe cumplir, i=i+1 
                                                        //significa que despues de cada iteracion a i se le suma 1.
                                                        //begin: gen_celdas significa que se comienza un bloque de nombre gen_celdas.
        //codigo para instanciar la celda tipica
        celda_tipica_e uut_tipica(
            .A(A[i]), //el bit i de A se conecta al puerto A, en este caso, se hace asi para que a cada celda tipica le quede un bit,
            .B(B[i]),
            .w(W_temp[i]), //el bit i-1 se conecta a w
            .W(W_temp[i+1])//el bit i+1 de Y se conecta al puerto Y.
        );          
        end
    endgenerate 
    celda_final_e uut_final_e( //Ya que la celda final es diferente para este diseno, conectamos los puertos A,B y W al bit numero 'N' 
    .W(W_temp[N]),
    .Z(Z));
    assign W_out =  Z;//Misma logica para Z.
endmodule

ESTRUCTURAL/Comparador_tb.v
//Proyecto Final de Digitales,C01263,B82600,B86941.
//Implementacion Estructural al caso DERECHA a IZQUIERDA.
`timescale 1ns/1ns
`include "Comparador .v"

//*Importante:Para GtkWave, el valor que importa es W_out. Para efectos del proyecto, la salida Z que nos piden en este caso va a ser W, se trae asi porque asi se hizo 
//diseño.
module Comparador_tb #(parameter N = 1);//SI VAN A CAMBIAR EL PARAMETRO, TANTO ESTE COMO EL DEL OTRO MODULO DEBEN SER IGUALES!!!!
  reg [N-1:0] A, B;                                   
  wire W_out;
  reg reset;
  

  // Instanciación del módulo bajo prueba

   initial begin
        reset=1'b1;//se agrega un reinicio para garantizar que al inicio de cada prueba, las ondas empiecen en 0
        #10//ademas, se agrega un retardo despues de cada reset.
        reset=1'b0;
    end
  Comparador uut ( 
    .A(A),
    .B(B),
    .W_out(W_out)
  );

  // Lógica para aplicar pruebas a la red.
  initial begin
    #10 reset = 1;
    #10 reset = 0;
    // Asigno valores iniciales a las entradas
    $dumpfile ("Comparador_tb.vcd");//Para generar el .vcd para gtkwave
    $dumpvars (0,uut);
        
    //Se decidio aplicar pruebas con valores aleatorios. Estos valores aleatorios, se generan de un rango de 0 al parametro N. 
    //Esto significa que, por ejemplo, si N=7, A y B van a ser palabras de 7 bits, y dentro de esos 7 bits los 0s y 1s se generan
    //de manera aleatoria. Esto garantiza probar combinaciones diferentes de bits, en vez de tener que hacerlas manualmente.
    //El proceso es eficiente, y pone aun mas a prueba el funcionamiento de la red.
    //Prueba 1
    A = $urandom_range(0, (1<<N)-1);
    B = $urandom_range(0, (1<<N)-1);
    #1000 reset = 1;//retardo despues del reset
    #10 reset = 0;//retardo despues del reset
    #1000; //retardo
    $display("Valor: A = %b, B = %b, W_out = %b", A, B, W_out);//esto es para que en la terminal, se impriman los valores del comparador
                                                              //para garantizar que funcione.
    //A partir de aca, se copia y pega las pruebas deseadas a correr. Mientras mas, mejor. Se decidio en ejecutar 10 pruebas de manera arbitraria.
    //Prueba 2
    A = $urandom_range(0, (1<<N)-1);
    B = $urandom_range(0, (1<<N)-1);
    #1000 reset = 1;
    #10 reset = 0;
    #1000;  
    $display("Valor: A = %b, B = %b, W_out = %b", A, B, W_out);
  //Prueba 3
    A = $urandom_range(0, (1<<N)-1);
    B = $urandom_range(0, (1<<N)-1);
    #1000 reset = 1;
    #10 reset = 0;
    #1000;  
    $display("Valor: A = %b, B = %b, W_out = %b", A, B, W_out);
  //Prueba 3
    A = $urandom_range(0, (1<<N)-1);
    B = $urandom_range(0, (1<<N)-1);
    #1000 reset = 1;
    #10 reset = 0;
    #1000;  
    $display("Valor: A = %b, B = %b,W_out = %b", A, B,W_out);
  //Prueba 4
    A = $urandom_range(0, (1<<N)-1);
    B = $urandom_range(0, (1<<N)-1);
    #1000 reset = 1;
    #10 reset = 0;
    #1000;  
    $display("Valor: A = %b, B = %b,W_out = %b", A, B, W_out);

  //Prueba 5
    A = $urandom_range(0, (1<<N)-1);
    B = $urandom_range(0, (1<<N)-1);
    #1000 reset = 1;
    #10 reset = 0;
    #1000;  
    $display("Valor: A = %b, B = %b, W_out = %b", A, B, W_out);

    //Prueba 6
    A = $urandom_range(0, (1<<N)-1);
    B = $urandom_range(0, (1<<N)-1);
    #1000 reset = 1;
    #10 reset = 0;
    #1000;  
    $display("Valor: A = %b, B = %b, W_out = %b", A, B,W_out);
    
    //Prueba 7
    A = $urandom_range(0, (1<<N)-1);
    B = $urandom_range(0, (1<<N)-1);
    #1000 reset = 1;
    #10 reset = 0;
    #1000;  
    $display("Valor: A = %b, B = %b, W_out = %b", A, B, W_out);

    //Prueba 8
    A = $urandom_range(0, (1<<N)-1);
    B = $urandom_range(0, (1<<N)-1);
    #1000 reset = 1;
    #10 reset = 0;
    #1000;  
    $display("Valor: A = %b, B = %b, W_out = %b", A, B, W_out);

    //Prueba 9
    A = $urandom_range(0, (1<<N)-1);
    B = $urandom_range(0, (1<<N)-1);
    #1000 reset = 1;
    #10 reset = 0;
    #1000;  
    $display("Valor: A = %b, B = %b, W_out  = %b", A, B, W_out);

    //Prueba 10
    A = $urandom_range(0, (1<<N)-1);
    B = $urandom_range(0, (1<<N)-1);
    #1000 reset = 1;
    #10 reset = 0;
    #1000;  
    $display("Valor: A = %b, B = %b, W_out = %b", A, B, W_out);

    // Mostrar resultados
    $display("end of test.");

    // Si se desea generar otro 'set' de datos random, se debe borrar el .vcd y el .vvp, y cambiar el parametro N.
  end
endmodule

ESTRUCTURAL/Comparador_tb.vcd
$date
	Wed Nov 29 07:40:16 2023
$end
$version
	Icarus Verilog
$end
$timescale
	1ns
$end
$scope module Comparador_tb $end
$scope module uut $end
$var wire 1 ! A $end
$var wire 1 " B $end
$var wire 1 # W_out $end
$var wire 1 $ Z $end
$var wire 2 % W_temp [1:0] $end
$scope begin gen_celdas[0] $end
$scope module uut_tipica $end
$var wire 1 ! A $end
$var wire 1 " B $end
$var wire 1 & w $end
$var wire 1 ' wB_neg_OR $end
$var wire 1 ( wA_OR $end
$var wire 1 ) W $end
$var wire 1 * OR1 $end
$var wire 1 + B_neg $end
$var wire 1 , AB_neg_OR $end
$scope module comp_AND_ct1 $end
$var wire 1 ' AND $end
$var wire 1 & A_and $end
$var wire 1 + B_and $end
$upscope $end
$scope module comp_AND_ct2 $end
$var wire 1 ( AND $end
$var wire 1 & A_and $end
$var wire 1 ! B_and $end
$upscope $end
$scope module comp_AND_ct3 $end
$var wire 1 , AND $end
$var wire 1 ! A_and $end
$var wire 1 + B_and $end
$upscope $end
$scope module comp_OR_ct1 $end
$var wire 1 ' A_or $end
$var wire 1 ( B_or $end
$var wire 1 * OR $end
$upscope $end
$scope module comp_OR_ct2 $end
$var wire 1 * A_or $end
$var wire 1 , B_or $end
$var wire 1 ) OR $end
$upscope $end
$scope module inversorB $end
$var wire 1 " entrada $end
$var wire 1 + salida $end
$upscope $end
$upscope $end
$upscope $end
$scope module uut_final_e $end
$var wire 1 - A $end
$var wire 1 . B $end
$var wire 1 / W $end
$var wire 1 $ Z $end
$scope module inversorW_cf $end
$var wire 1 / entrada $end
$var wire 1 $ salida $end
$upscope $end
$upscope $end
$scope module uut_inicial $end
$var wire 1 ! A $end
$var wire 1 " B $end
$var wire 1 0 W $end
$var wire 1 1 B_neg $end
$scope module comp_AND_ci $end
$var wire 1 0 AND $end
$var wire 1 ! A_and $end
$var wire 1 1 B_and $end
$upscope $end
$scope module inversorB $end
$var wire 1 " entrada $end
$var wire 1 1 salida $end
$upscope $end
$upscope $end
$upscope $end
$upscope $end
$enddefinitions $end
#20
$dumpvars
11
10
1/
z.
z-
1,
1+
1*
1)
1(
1'
1&
b11 %
0$
0#
0"
1!
$end
#2030
1#
1$
0/
0)
0*
0'
0&
0(
0,
b0 %
00
0!
#4040
1#
1$
0*
0/
0(
0)
0&
0+
01
0,
b0 %
00
1"
1!
#6050
1+
11
0"
0!
#8060
1#
1$
0*
0/
0(
0)
0&
0+
01
0,
b0 %
00
1"
1!
#14090
0#
0$
1*
1/
1'
1(
1)
1&
1,
b11 %
10
1+
11
0"
#16100
1#
1$
0/
0)
0*
0'
0&
0(
0,
b0 %
00
0!
#18110
0#
0$
1*
1/
1'
1(
1)
1&
1,
b11 %
10
1!
#20120
1#
1$
0/
0)
0*
0'
0&
0+
01
0(
0,
b0 %
00
1"
0!
